{
  "$schema": "https://developer.microsoft.com/json-schemas/fabric/item/report/definition/visualContainer/2.8.0/schema.json",
  "name": "d35dcca3135d40210ac1",
  "position": {
    "x": 15.026187134865205,
    "y": 0,
    "z": 1000,
    "height": 38.143398111580908,
    "width": 236.95141251133595,
    "tabOrder": 8000
  },
  "visual": {
    "visualType": "textbox",
    "objects": {
      "general": [
        {
          "properties": {
            "paragraphs": [
              {
                "textRuns": [
                  {
                    "value": "Reclamos",
                    "textStyle": {
                      "fontWeight": "bold",
                      "fontFamily": "DIN",
                      "fontSize": "18pt",
                      "color": "#0d6abf"
                    }
                  }
                ]
              }
            ]
          }
        }
      ]
    },
    "visualContainerObjects": {
      "background": [
        {
          "properties": {
            "transparency": {
              "expr": {
                "Literal": {
                  "Value": "100D"
                }
              }
            }
          }
        }
      ]
    },
    "drillFilterOtherVisuals": true
  }
}